summary_stack_obsidian_mcp_server/__init__.py
summary_stack_obsidian_mcp_server/__main__.py
summary_stack_obsidian_mcp_server/config.py
summary_stack_obsidian_mcp_server/models.py
summary_stack_obsidian_mcp_server/server.py
summary_stack_obsidian_mcp_server/services/__init__.py
summary_stack_obsidian_mcp_server/services/api_client.py
summary_stack_obsidian_mcp_server/services/vault_service.py
summary_stack_obsidian_mcp_server-2026.1.31.1050.dist-info/METADATA
summary_stack_obsidian_mcp_server-2026.1.31.1050.dist-info/WHEEL
summary_stack_obsidian_mcp_server-2026.1.31.1050.dist-info/entry_points.txt
summary_stack_obsidian_mcp_server-2026.1.31.1050.dist-info/RECORD
