Metadata-Version: 2.4
Name: summary-stack-obsidian-mcp-server
Version: 2026.1.31.1050
Summary: MCP Server for creating Summary Stack notes in local Obsidian vaults
Project-URL: Homepage, https://summarystack.ai
Project-URL: Repository, https://github.com/tomschreck/cannon-collective-nx
Author-email: Tom Schreck <tom@arta.ing>
License: MIT
Keywords: knowledge-management,mcp,model-context-protocol,notes,obsidian,summary-stack
Classifier: Development Status :: 4 - Beta
Classifier: Intended Audience :: Developers
Classifier: License :: OSI Approved :: MIT License
Classifier: Programming Language :: Python :: 3
Classifier: Programming Language :: Python :: 3.12
Classifier: Programming Language :: Python :: 3.13
Classifier: Typing :: Typed
Requires-Python: >=3.12
Requires-Dist: fastmcp>=2.0.0
Requires-Dist: httpx<1.0,>=0.28.0
Requires-Dist: pydantic<3.0,>=2.12.0
Requires-Dist: pyyaml<7.0,>=6.0.0
Requires-Dist: summary-stack-mcp-core>=0.1.0
